{"type":"Chunk","body":[{"type":"LocalStatement","variables":[{"type":"Identifier","name":"CONSTANTS"}],"init":[{"type":"TableConstructorExpression","fields":[]}]},{"type":"AssignmentStatement","variables":[{"type":"IndexExpression","base":{"type":"Identifier","name":"CONSTANTS"},"index":{"type":"StringLiteral","value":"STREAK_MOD","raw":"\"STREAK_MOD\""}}],"init":[{"type":"NumericLiteral","value":5,"raw":"5"}]},{"type":"AssignmentStatement","variables":[{"type":"IndexExpression","base":{"type":"Identifier","name":"CONSTANTS"},"index":{"type":"StringLiteral","value":"STREAK_BONUS","raw":"\"STREAK_BONUS\""}}],"init":[{"type":"TableConstructorExpression","fields":[{"type":"TableValue","value":{"type":"NumericLiteral","value":1,"raw":"1"}},{"type":"TableValue","value":{"type":"NumericLiteral","value":5,"raw":"5"}},{"type":"TableValue","value":{"type":"NumericLiteral","value":10,"raw":"10"}}]}]},{"type":"FunctionDeclaration","identifier":{"type":"Identifier","name":"onStartup"},"isLocal":false,"parameters":[{"type":"Identifier","name":"self"}],"body":[{"type":"CallStatement","expression":{"type":"CallExpression","base":{"type":"MemberExpression","indexer":".","identifier":{"type":"Identifier","name":"randomseed"},"base":{"type":"Identifier","name":"math"}},"arguments":[{"type":"CallExpression","base":{"type":"MemberExpression","indexer":".","identifier":{"type":"Identifier","name":"time"},"base":{"type":"Identifier","name":"os"}},"arguments":[]}]}},{"type":"CallStatement","expression":{"type":"TableCallExpression","base":{"type":"MemberExpression","indexer":":","identifier":{"type":"Identifier","name":"SetSmashableParams"},"base":{"type":"Identifier","name":"self"}},"arguments":{"type":"TableConstructorExpression","fields":[{"type":"TableKeyString","key":{"type":"Identifier","name":"fExplodeFactor"},"value":{"type":"NumericLiteral","value":2.5,"raw":"2.5"}}]}}}]},{"type":"FunctionDeclaration","identifier":{"type":"Identifier","name":"onGetActivityPoints"},"isLocal":false,"parameters":[{"type":"Identifier","name":"self"},{"type":"Identifier","name":"msg"}],"body":[{"type":"LocalStatement","variables":[{"type":"Identifier","name":"SpawnData"}],"init":[{"type":"CallExpression","base":{"type":"MemberExpression","indexer":":","identifier":{"type":"Identifier","name":"GetVar"},"base":{"type":"Identifier","name":"self"}},"arguments":[{"type":"StringLiteral","value":"SpawnData","raw":"\"SpawnData\""}]}]},{"type":"IfStatement","clauses":[{"type":"IfClause","condition":{"type":"Identifier","name":"SpawnData","inParens":true},"body":[{"type":"IfStatement","clauses":[{"type":"IfClause","condition":{"type":"MemberExpression","indexer":".","identifier":{"type":"Identifier","name":"sdScore"},"base":{"type":"Identifier","name":"SpawnData"},"inParens":true},"body":[{"type":"AssignmentStatement","variables":[{"type":"MemberExpression","indexer":".","identifier":{"type":"Identifier","name":"points"},"base":{"type":"Identifier","name":"msg"}}],"init":[{"type":"MemberExpression","indexer":".","identifier":{"type":"Identifier","name":"sdScore"},"base":{"type":"Identifier","name":"SpawnData"},"inParens":true}]}]}]},{"type":"AssignmentStatement","variables":[{"type":"MemberExpression","indexer":".","identifier":{"type":"Identifier","name":"addTime"},"base":{"type":"Identifier","name":"msg"}}],"init":[{"type":"MemberExpression","indexer":".","identifier":{"type":"Identifier","name":"sdTimeScore"},"base":{"type":"Identifier","name":"SpawnData"}}]},{"type":"CallStatement","expression":{"type":"TableCallExpression","base":{"type":"MemberExpression","indexer":":","identifier":{"type":"Identifier","name":"SetActivityUserData"},"base":{"type":"Identifier","name":"self"}},"arguments":{"type":"TableConstructorExpression","fields":[{"type":"TableKeyString","key":{"type":"Identifier","name":"userID"},"value":{"type":"MemberExpression","indexer":".","identifier":{"type":"Identifier","name":"userID"},"base":{"type":"TableCallExpression","base":{"type":"MemberExpression","indexer":":","identifier":{"type":"Identifier","name":"GetActivityUser"},"base":{"type":"CallExpression","base":{"type":"MemberExpression","indexer":":","identifier":{"type":"Identifier","name":"GetZoneControlID"},"base":{"type":"Identifier","name":"GAMEOBJ"}},"arguments":[]}},"arguments":{"type":"TableConstructorExpression","fields":[]}}}},{"type":"TableKeyString","key":{"type":"Identifier","name":"typeIndex"},"value":{"type":"NumericLiteral","value":5,"raw":"5"}},{"type":"TableKeyString","key":{"type":"Identifier","name":"value"},"value":{"type":"MemberExpression","indexer":".","identifier":{"type":"Identifier","name":"points"},"base":{"type":"Identifier","name":"msg"}}}]}}}]}]},{"type":"ReturnStatement","arguments":[{"type":"Identifier","name":"msg"}]}]},{"type":"FunctionDeclaration","identifier":{"type":"Identifier","name":"NotifyParentToRespawn"},"isLocal":false,"parameters":[{"type":"Identifier","name":"self"}],"body":[{"type":"LocalStatement","variables":[{"type":"Identifier","name":"parentID"}],"init":[{"type":"CallExpression","base":{"type":"MemberExpression","indexer":":","identifier":{"type":"Identifier","name":"GetObjectByID"},"base":{"type":"Identifier","name":"GAMEOBJ"}},"arguments":[{"type":"CallExpression","base":{"type":"MemberExpression","indexer":":","identifier":{"type":"Identifier","name":"GetVar"},"base":{"type":"Identifier","name":"self"}},"arguments":[{"type":"StringLiteral","value":"My_Parent_ID","raw":"\"My_Parent_ID\""}]}]}]},{"type":"IfStatement","clauses":[{"type":"IfClause","condition":{"type":"CallExpression","base":{"type":"MemberExpression","indexer":":","identifier":{"type":"Identifier","name":"Exists"},"base":{"type":"Identifier","name":"parentID"}},"arguments":[]},"body":[{"type":"CallStatement","expression":{"type":"TableCallExpression","base":{"type":"MemberExpression","indexer":":","identifier":{"type":"Identifier","name":"NotifyObject"},"base":{"type":"Identifier","name":"parentID"}},"arguments":{"type":"TableConstructorExpression","fields":[{"type":"TableKeyString","key":{"type":"Identifier","name":"ObjIDSender"},"value":{"type":"Identifier","name":"self"}},{"type":"TableKeyString","key":{"type":"Identifier","name":"name"},"value":{"type":"StringLiteral","value":"FinishedPath","raw":"\"FinishedPath\""}}]}}}]}]},{"type":"CallStatement","expression":{"type":"CallExpression","base":{"type":"Identifier","name":"Despawn"},"arguments":[{"type":"Identifier","name":"self"}]}}]},{"type":"FunctionDeclaration","identifier":{"type":"Identifier","name":"onArrived"},"isLocal":false,"parameters":[{"type":"Identifier","name":"self"},{"type":"Identifier","name":"msg"}],"body":[{"type":"IfStatement","clauses":[{"type":"IfClause","condition":{"type":"BinaryExpression","operator":"==","left":{"type":"MemberExpression","indexer":".","identifier":{"type":"Identifier","name":"isLastPoint"},"base":{"type":"Identifier","name":"msg"}},"right":{"type":"BooleanLiteral","value":true,"raw":"true"},"inParens":true},"body":[{"type":"CallStatement","expression":{"type":"CallExpression","base":{"type":"Identifier","name":"NotifyParentToRespawn"},"arguments":[{"type":"Identifier","name":"self"}]}},{"type":"ReturnStatement","arguments":[]}]}]},{"type":"CallStatement","expression":{"type":"CallExpression","base":{"type":"Identifier","name":"ChangeSpeed"},"arguments":[{"type":"Identifier","name":"self"}]}},{"type":"IfStatement","clauses":[{"type":"IfClause","condition":{"type":"MemberExpression","indexer":".","identifier":{"type":"Identifier","name":"actions"},"base":{"type":"Identifier","name":"msg"},"inParens":true},"body":[{"type":"IfStatement","clauses":[{"type":"IfClause","condition":{"type":"BinaryExpression","operator":"==","left":{"type":"MemberExpression","indexer":".","identifier":{"type":"Identifier","name":"name"},"base":{"type":"IndexExpression","base":{"type":"MemberExpression","indexer":".","identifier":{"type":"Identifier","name":"actions"},"base":{"type":"Identifier","name":"msg"}},"index":{"type":"NumericLiteral","value":1,"raw":"1"}}},"right":{"type":"StringLiteral","value":"PlayAim","raw":"\"PlayAim\""}},"body":[{"type":"LocalStatement","variables":[{"type":"Identifier","name":"aimName"}],"init":[{"type":"MemberExpression","indexer":".","identifier":{"type":"Identifier","name":"value"},"base":{"type":"IndexExpression","base":{"type":"MemberExpression","indexer":".","identifier":{"type":"Identifier","name":"actions"},"base":{"type":"Identifier","name":"msg"}},"index":{"type":"NumericLiteral","value":1,"raw":"1"}}}]},{"type":"LocalStatement","variables":[{"type":"Identifier","name":"anim_time"}],"init":[{"type":"MemberExpression","indexer":".","identifier":{"type":"Identifier","name":"time"},"base":{"type":"TableCallExpression","base":{"type":"MemberExpression","indexer":":","identifier":{"type":"Identifier","name":"GetAnimationTime"},"base":{"type":"Identifier","name":"self"}},"arguments":{"type":"TableConstructorExpression","fields":[{"type":"TableKeyString","key":{"type":"Identifier","name":"animationID"},"value":{"type":"Identifier","name":"aimName"}}]}}}]},{"type":"IfStatement","clauses":[{"type":"IfClause","condition":{"type":"BinaryExpression","operator":">","left":{"type":"CallExpression","base":{"type":"Identifier","name":"tonumber"},"arguments":[{"type":"Identifier","name":"anim_time"}]},"right":{"type":"NumericLiteral","value":0,"raw":"0"},"inParens":true},"body":[{"type":"CallStatement","expression":{"type":"TableCallExpression","base":{"type":"MemberExpression","indexer":":","identifier":{"type":"Identifier","name":"PlayAnimation"},"base":{"type":"Identifier","name":"self"}},"arguments":{"type":"TableConstructorExpression","fields":[{"type":"TableKeyString","key":{"type":"Identifier","name":"animationID"},"value":{"type":"Identifier","name":"aimName"}}]}}}]}]}]}]}]}]},{"type":"CallStatement","expression":{"type":"CallExpression","base":{"type":"MemberExpression","indexer":":","identifier":{"type":"Identifier","name":"ContinueWaypoints"},"base":{"type":"Identifier","name":"self"}},"arguments":[]}}]},{"type":"FunctionDeclaration","identifier":{"type":"Identifier","name":"onTimerDone"},"isLocal":false,"parameters":[{"type":"Identifier","name":"self"},{"type":"Identifier","name":"msg"}],"body":[{"type":"IfStatement","clauses":[{"type":"IfClause","condition":{"type":"BinaryExpression","operator":"==","left":{"type":"MemberExpression","indexer":".","identifier":{"type":"Identifier","name":"name"},"base":{"type":"Identifier","name":"msg"}},"right":{"type":"StringLiteral","value":"ChangeSpeed","raw":"\"ChangeSpeed\""}},"body":[{"type":"LocalStatement","variables":[{"type":"Identifier","name":"ran"}],"init":[{"type":"CallExpression","base":{"type":"MemberExpression","indexer":".","identifier":{"type":"Identifier","name":"random"},"base":{"type":"Identifier","name":"math"}},"arguments":[{"type":"NumericLiteral","value":1,"raw":"1"},{"type":"NumericLiteral","value":4,"raw":"4"}]}]},{"type":"CallStatement","expression":{"type":"TableCallExpression","base":{"type":"MemberExpression","indexer":":","identifier":{"type":"Identifier","name":"SetPathingSpeed"},"base":{"type":"Identifier","name":"self"}},"arguments":{"type":"TableConstructorExpression","fields":[{"type":"TableKeyString","key":{"type":"Identifier","name":"speed"},"value":{"type":"Identifier","name":"ran"}}]}}},{"type":"CallStatement","expression":{"type":"CallExpression","base":{"type":"MemberExpression","indexer":":","identifier":{"type":"Identifier","name":"AddTimerWithCancel"},"base":{"type":"CallExpression","base":{"type":"MemberExpression","indexer":":","identifier":{"type":"Identifier","name":"GetTimer"},"base":{"type":"Identifier","name":"GAMEOBJ"}},"arguments":[]}},"arguments":[{"type":"NumericLiteral","value":5,"raw":"5.0"},{"type":"StringLiteral","value":"ChangeSpeed","raw":"\"ChangeSpeed\""},{"type":"Identifier","name":"self"}]}}]},{"type":"ElseifClause","condition":{"type":"BinaryExpression","operator":"==","left":{"type":"MemberExpression","indexer":".","identifier":{"type":"Identifier","name":"name"},"base":{"type":"Identifier","name":"msg"}},"right":{"type":"StringLiteral","value":"Despawn","raw":"\"Despawn\""}},"body":[{"type":"CallStatement","expression":{"type":"CallExpression","base":{"type":"MemberExpression","indexer":":","identifier":{"type":"Identifier","name":"CancelAllTimers"},"base":{"type":"CallExpression","base":{"type":"MemberExpression","indexer":":","identifier":{"type":"Identifier","name":"GetTimer"},"base":{"type":"Identifier","name":"GAMEOBJ"}},"arguments":[]}},"arguments":[{"type":"Identifier","name":"self"}]}},{"type":"CallStatement","expression":{"type":"TableCallExpression","base":{"type":"MemberExpression","indexer":":","identifier":{"type":"Identifier","name":"Die"},"base":{"type":"Identifier","name":"self"}},"arguments":{"type":"TableConstructorExpression","fields":[{"type":"TableKeyString","key":{"type":"Identifier","name":"killerID"},"value":{"type":"Identifier","name":"self"}},{"type":"TableKeyString","key":{"type":"Identifier","name":"killType"},"value":{"type":"StringLiteral","value":"SILENT","raw":"\"SILENT\""}}]}}}]}]}]},{"type":"FunctionDeclaration","identifier":{"type":"Identifier","name":"ChangeSpeed"},"isLocal":false,"parameters":[{"type":"Identifier","name":"self"}],"body":[{"type":"LocalStatement","variables":[{"type":"Identifier","name":"SpawnData"}],"init":[{"type":"CallExpression","base":{"type":"MemberExpression","indexer":":","identifier":{"type":"Identifier","name":"GetVar"},"base":{"type":"Identifier","name":"self"}},"arguments":[{"type":"StringLiteral","value":"SpawnData","raw":"\"SpawnData\""}]}]},{"type":"IfStatement","clauses":[{"type":"IfClause","condition":{"type":"Identifier","name":"SpawnData","inParens":true},"body":[{"type":"IfStatement","clauses":[{"type":"IfClause","condition":{"type":"LogicalExpression","operator":"and","left":{"type":"BinaryExpression","operator":"==","left":{"type":"MemberExpression","indexer":".","identifier":{"type":"Identifier","name":"sdChangeSpeed"},"base":{"type":"Identifier","name":"SpawnData"}},"right":{"type":"BooleanLiteral","value":true,"raw":"true"},"inParens":true},"right":{"type":"BinaryExpression","operator":"<=","left":{"type":"CallExpression","base":{"type":"MemberExpression","indexer":".","identifier":{"type":"Identifier","name":"random"},"base":{"type":"Identifier","name":"math"}},"arguments":[]},"right":{"type":"MemberExpression","indexer":".","identifier":{"type":"Identifier","name":"sdSpeedChance"},"base":{"type":"Identifier","name":"SpawnData"}},"inParens":true},"inParens":true},"body":[{"type":"LocalStatement","variables":[{"type":"Identifier","name":"newSpeed"}],"init":[{"type":"CallExpression","base":{"type":"MemberExpression","indexer":".","identifier":{"type":"Identifier","name":"random"},"base":{"type":"Identifier","name":"math"}},"arguments":[{"type":"MemberExpression","indexer":".","identifier":{"type":"Identifier","name":"sdMinSpeed"},"base":{"type":"Identifier","name":"SpawnData"}},{"type":"MemberExpression","indexer":".","identifier":{"type":"Identifier","name":"sdMaxSpeed"},"base":{"type":"Identifier","name":"SpawnData"}}]}]},{"type":"CallStatement","expression":{"type":"TableCallExpression","base":{"type":"MemberExpression","indexer":":","identifier":{"type":"Identifier","name":"SetPathingSpeed"},"base":{"type":"Identifier","name":"self"}},"arguments":{"type":"TableConstructorExpression","fields":[{"type":"TableKeyString","key":{"type":"Identifier","name":"speed"},"value":{"type":"Identifier","name":"newSpeed"}}]}}}]}]}]}]}]},{"type":"FunctionDeclaration","identifier":{"type":"Identifier","name":"Despawn"},"isLocal":false,"parameters":[{"type":"Identifier","name":"self"}],"body":[{"type":"LocalStatement","variables":[{"type":"Identifier","name":"SpawnData"}],"init":[{"type":"CallExpression","base":{"type":"MemberExpression","indexer":":","identifier":{"type":"Identifier","name":"GetVar"},"base":{"type":"Identifier","name":"self"}},"arguments":[{"type":"StringLiteral","value":"SpawnData","raw":"\"SpawnData\""}]}]},{"type":"IfStatement","clauses":[{"type":"IfClause","condition":{"type":"Identifier","name":"SpawnData","inParens":true},"body":[{"type":"IfStatement","clauses":[{"type":"IfClause","condition":{"type":"BinaryExpression","operator":"==","left":{"type":"MemberExpression","indexer":".","identifier":{"type":"Identifier","name":"sdDespawnTime"},"base":{"type":"Identifier","name":"SpawnData"}},"right":{"type":"BooleanLiteral","value":true,"raw":"true"},"inParens":true},"body":[{"type":"LocalStatement","variables":[{"type":"Identifier","name":"timeout"}],"init":[{"type":"NumericLiteral","value":1,"raw":"1"}]},{"type":"IfStatement","clauses":[{"type":"IfClause","condition":{"type":"BinaryExpression","operator":"==","left":{"type":"MemberExpression","indexer":".","identifier":{"type":"Identifier","name":"sdMovingPlat"},"base":{"type":"Identifier","name":"SpawnData"}},"right":{"type":"BooleanLiteral","value":true,"raw":"true"},"inParens":true},"body":[{"type":"AssignmentStatement","variables":[{"type":"Identifier","name":"timeout"}],"init":[{"type":"NumericLiteral","value":2,"raw":"2"}]}]}]},{"type":"CallStatement","expression":{"type":"CallExpression","base":{"type":"MemberExpression","indexer":":","identifier":{"type":"Identifier","name":"AddTimerWithCancel"},"base":{"type":"CallExpression","base":{"type":"MemberExpression","indexer":":","identifier":{"type":"Identifier","name":"GetTimer"},"base":{"type":"Identifier","name":"GAMEOBJ"}},"arguments":[]}},"arguments":[{"type":"Identifier","name":"timeout"},{"type":"StringLiteral","value":"Despawn","raw":"\"Despawn\""},{"type":"Identifier","name":"self"}]}}]}]}]},{"type":"ElseClause","body":[{"type":"CallStatement","expression":{"type":"CallExpression","base":{"type":"MemberExpression","indexer":":","identifier":{"type":"Identifier","name":"CancelAllTimers"},"base":{"type":"CallExpression","base":{"type":"MemberExpression","indexer":":","identifier":{"type":"Identifier","name":"GetTimer"},"base":{"type":"Identifier","name":"GAMEOBJ"}},"arguments":[]}},"arguments":[{"type":"Identifier","name":"self"}]}},{"type":"CallStatement","expression":{"type":"TableCallExpression","base":{"type":"MemberExpression","indexer":":","identifier":{"type":"Identifier","name":"Die"},"base":{"type":"Identifier","name":"self"}},"arguments":{"type":"TableConstructorExpression","fields":[{"type":"TableKeyString","key":{"type":"Identifier","name":"killerID"},"value":{"type":"Identifier","name":"self"}},{"type":"TableKeyString","key":{"type":"Identifier","name":"killType"},"value":{"type":"StringLiteral","value":"SILENT","raw":"\"SILENT\""}}]}}}]}]}]}],"comments":[{"type":"Comment","value":" ================================================","raw":"-- ================================================"},{"type":"Comment","value":" SG Target Script","raw":"-- SG Target Script"},{"type":"Comment","value":" Server Side","raw":"-- Server Side"},{"type":"Comment","value":" updated 9/30/10 mrb... changed mover despawn time","raw":"-- updated 9/30/10 mrb... changed mover despawn time"},{"type":"Comment","value":" ================================================","raw":"-- ================================================"},{"type":"Comment","value":"------------------------------------------------------------","raw":"--------------------------------------------------------------"},{"type":"Comment","value":" Includes","raw":"-- Includes"},{"type":"Comment","value":"------------------------------------------------------------","raw":"--------------------------------------------------------------"},{"type":"Comment","value":"require('o_mis')","raw":"--require('o_mis')"},{"type":"Comment","value":"------------------------------------------------------------","raw":"--------------------------------------------------------------"},{"type":"Comment","value":" Startup of the object","raw":"-- Startup of the object"},{"type":"Comment","value":"------------------------------------------------------------","raw":"--------------------------------------------------------------"},{"type":"Comment","value":" pick a random explode factor","raw":"-- pick a random explode factor"},{"type":"Comment","value":" set explode factor","raw":"-- set explode factor"},{"type":"Comment","value":"------------------------------------------------------------","raw":"--------------------------------------------------------------"},{"type":"Comment","value":" Get the score for the target","raw":"-- Get the score for the target"},{"type":"Comment","value":"------------------------------------------------------------","raw":"--------------------------------------------------------------"},{"type":"Comment","value":"------------------------------------------------------------","raw":"--------------------------------------------------------------"},{"type":"Comment","value":" continue doign waypoints","raw":"-- continue doign waypoints"},{"type":"Comment","value":" @TODO: modify speed/path/etc","raw":"-- @TODO: modify speed/path/etc"},{"type":"Comment","value":"------------------------------------------------------------","raw":"--------------------------------------------------------------"},{"type":"Comment","value":" do speed change","raw":"-- do speed change"},{"type":"Comment","value":"------------------------------------------------------------","raw":"--------------------------------------------------------------"},{"type":"Comment","value":" Timers","raw":"-- Timers"},{"type":"Comment","value":"------------------------------------------------------------","raw":"--------------------------------------------------------------"},{"type":"Comment","value":" Change the speed every 5 seconds","raw":"-- Change the speed every 5 seconds"},{"type":"Comment","value":" pick a random speed","raw":"-- pick a random speed"},{"type":"Comment","value":"------------------------------------------------------------","raw":"--------------------------------------------------------------"},{"type":"Comment","value":" Try to change the targets speed","raw":"-- Try to change the targets speed"},{"type":"Comment","value":"------------------------------------------------------------","raw":"--------------------------------------------------------------"},{"type":"Comment","value":" get spawn data","raw":"-- get spawn data"},{"type":"Comment","value":" should we try to change speed?","raw":"-- should we try to change speed?"},{"type":"Comment","value":" get a speed","raw":"-- get a speed"},{"type":"Comment","value":" set the new speed","raw":"-- set the new speed"},{"type":"Comment","value":"------------------------------------------------------------","raw":"--------------------------------------------------------------"},{"type":"Comment","value":" Try to despawn the target","raw":"-- Try to despawn the target"},{"type":"Comment","value":"------------------------------------------------------------","raw":"--------------------------------------------------------------"},{"type":"Comment","value":" get spawn data","raw":"-- get spawn data"},{"type":"Comment","value":" should we try to despawn?","raw":"-- should we try to despawn?"},{"type":"Comment","value":" use 10 second timeout so platforms aren't killed on the client before they finish their path","raw":"-- use 10 second timeout so platforms aren't killed on the client before they finish their path"}]}