{"type":"Chunk","body":[{"type":"CallStatement","expression":{"type":"CallExpression","base":{"type":"Identifier","name":"require"},"arguments":[{"type":"StringLiteral","value":"o_mis","raw":"'o_mis'"}]}},{"type":"FunctionDeclaration","identifier":{"type":"Identifier","name":"onStartup"},"isLocal":false,"parameters":[{"type":"Identifier","name":"self"}],"body":[]},{"type":"FunctionDeclaration","identifier":{"type":"Identifier","name":"onUse"},"isLocal":false,"parameters":[{"type":"Identifier","name":"self"},{"type":"Identifier","name":"msg"}],"body":[{"type":"LocalStatement","variables":[{"type":"Identifier","name":"targetGroup"}],"init":[{"type":"CallExpression","base":{"type":"MemberExpression","indexer":":","identifier":{"type":"Identifier","name":"GetVar"},"base":{"type":"Identifier","name":"self"}},"arguments":[{"type":"StringLiteral","value":"TargetGroup","raw":"\"TargetGroup\""}]}]},{"type":"IfStatement","clauses":[{"type":"IfClause","condition":{"type":"Identifier","name":"targetGroup","inParens":true},"body":[{"type":"CallStatement","expression":{"type":"CallExpression","base":{"type":"Identifier","name":"storeObjectByName"},"arguments":[{"type":"Identifier","name":"self"},{"type":"StringLiteral","value":"myUser","raw":"\"myUser\""},{"type":"MemberExpression","indexer":".","identifier":{"type":"Identifier","name":"user"},"base":{"type":"Identifier","name":"msg"}}]}},{"type":"LocalStatement","variables":[{"type":"Identifier","name":"objects"}],"init":[{"type":"MemberExpression","indexer":".","identifier":{"type":"Identifier","name":"objects"},"base":{"type":"TableCallExpression","base":{"type":"MemberExpression","indexer":":","identifier":{"type":"Identifier","name":"GetObjectsInGroup"},"base":{"type":"Identifier","name":"self"}},"arguments":{"type":"TableConstructorExpression","fields":[{"type":"TableKeyString","key":{"type":"Identifier","name":"group"},"value":{"type":"Identifier","name":"targetGroup"}}]}}}]},{"type":"ForNumericStatement","variable":{"type":"Identifier","name":"i"},"start":{"type":"NumericLiteral","value":1,"raw":"1"},"end":{"type":"CallExpression","base":{"type":"MemberExpression","indexer":".","identifier":{"type":"Identifier","name":"maxn"},"base":{"type":"Identifier","name":"table"}},"arguments":[{"type":"Identifier","name":"objects"}]},"step":null,"body":[{"type":"CallStatement","expression":{"type":"TableCallExpression","base":{"type":"MemberExpression","indexer":":","identifier":{"type":"Identifier","name":"FireEvent"},"base":{"type":"IndexExpression","base":{"type":"Identifier","name":"objects"},"index":{"type":"Identifier","name":"i"}}},"arguments":{"type":"TableConstructorExpression","fields":[{"type":"TableKeyString","key":{"type":"Identifier","name":"args"},"value":{"type":"StringLiteral","value":"button_activate","raw":"\"button_activate\""}},{"type":"TableKeyString","key":{"type":"Identifier","name":"senderID"},"value":{"type":"Identifier","name":"self"}}]}}}]}]}]}]}],"comments":[{"type":"Comment","value":"------------------------------------------------------------","raw":"--------------------------------------------------------------"},{"type":"Comment","value":" (SERVER SIDE) Script for the Lead the Monkey Minigame Button","raw":"-- (SERVER SIDE) Script for the Lead the Monkey Minigame Button"},{"type":"Comment","value":"","raw":"--"},{"type":"Comment","value":" :: \"TargetGroup\" config data needs to be set to the group of the game board","raw":"-- :: \"TargetGroup\" config data needs to be set to the group of the game board"},{"type":"Comment","value":"------------------------------------------------------------","raw":"--------------------------------------------------------------"},{"type":"Comment","value":"------------------------------------------------------------","raw":"--------------------------------------------------------------"},{"type":"Comment","value":" Includes","raw":"-- Includes"},{"type":"Comment","value":"------------------------------------------------------------","raw":"--------------------------------------------------------------"},{"type":"Comment","value":"------------------------------------------------------------","raw":"--------------------------------------------------------------"},{"type":"Comment","value":" Called when object is loaded into the level","raw":"-- Called when object is loaded into the level"},{"type":"Comment","value":"------------------------------------------------------------","raw":"--------------------------------------------------------------"},{"type":"Comment","value":"------------------------------------------------------------","raw":"--------------------------------------------------------------"},{"type":"Comment","value":" Called when object is used on the server","raw":"-- Called when object is used on the server"},{"type":"Comment","value":"------------------------------------------------------------","raw":"--------------------------------------------------------------"},{"type":"Comment","value":" get the target group config data","raw":"-- get the target group config data"},{"type":"Comment","value":" store who pressed me for a query later","raw":"-- store who pressed me for a query later"},{"type":"Comment","value":" send a notify to everyone (should only be a single object)","raw":"-- send a notify to everyone (should only be a single object)"}]}