{
  "LootTableIndex": 677,
  "elements": [
    {
      "MissionDrop": false,
      "id": 19216,
      "itemid": 7366,
      "sortPriority": 2140
    },
    {
      "MissionDrop": false,
      "id": 19217,
      "itemid": 7378,
      "sortPriority": 2150
    },
    {
      "MissionDrop": false,
      "id": 19218,
      "itemid": 7390,
      "sortPriority": 2160
    },
    {
      "MissionDrop": false,
      "id": 19219,
      "itemid": 7402,
      "sortPriority": 2170
    },
    {
      "MissionDrop": false,
      "id": 19220,
      "itemid": 7416,
      "sortPriority": 2180
    },
    {
      "MissionDrop": false,
      "id": 19221,
      "itemid": 7465,
      "sortPriority": 1140
    },
    {
      "MissionDrop": false,
      "id": 19222,
      "itemid": 7489,
      "sortPriority": 1150
    },
    {
      "MissionDrop": false,
      "id": 19223,
      "itemid": 7513,
      "sortPriority": 1160
    },
    {
      "MissionDrop": false,
      "id": 19224,
      "itemid": 7537,
      "sortPriority": 1170
    },
    {
      "MissionDrop": false,
      "id": 19225,
      "itemid": 7543,
      "sortPriority": 1180
    }
  ]
}
