{
  "HQ_valid": true,
  "_internalNotes": "3 IP 2 AP + Team IP Buff",
  "components": {
    "11": 6409,
    "2": 12685,
    "9": 0
  },
  "description": null,
  "displayName": "Mosaic Jester Cap",
  "gate_version": "auramar",
  "id": 12901,
  "interactionDistance": null,
  "locStatus": 2,
  "localize": true,
  "name": "Mosaic Jester Cap",
  "nametag": false,
  "npcTemplateID": null,
  "placeable": false,
  "skills": [
    {
      "AICombatWeight": 0,
      "castOnType": 1,
      "skillID": 361
    },
    {
      "AICombatWeight": 0,
      "castOnType": 1,
      "skillID": 371
    },
    {
      "AICombatWeight": 0,
      "castOnType": 0,
      "skillID": 1107
    }
  ],
  "type": "Loot"
}
