{
  "_embedded": {
    "BrickColors": [
      {
        "alpha": 1.0,
        "blue": 0.050980400294065475,
        "description": "Bright Red",
        "factoryValid": true,
        "green": 0.0,
        "id": 0,
        "legopaletteid": 21,
        "red": 0.8705880045890808,
        "validCharacters": 1,
        "validTypes": 14
      },
      {
        "alpha": 1.0,
        "blue": 0.6588230133056641,
        "description": "Bright Blue",
        "factoryValid": true,
        "green": 0.34117600321769714,
        "id": 1,
        "legopaletteid": 23,
        "red": 0.0,
        "validCharacters": 1,
        "validTypes": 14
      },
      {
        "alpha": 0.5882350206375122,
        "blue": 0.764706015586853,
        "description": "Transparent Medium reddish violet",
        "factoryValid": true,
        "green": 0.6156859993934631,
        "id": 65,
        "legopaletteid": 113,
        "red": 0.9333329796791077,
        "validCharacters": 0,
        "validTypes": 1
      },
      {
        "alpha": 1.0,
        "blue": 0.5450980067253113,
        "description": "Bright purple",
        "factoryValid": true,
        "green": 0.21568599343299866,
        "id": 130,
        "legopaletteid": 221,
        "red": 0.8705880045890808,
        "validCharacters": 0,
        "validTypes": 1
      },
      {
        "alpha": 1.0,
        "blue": 0.0,
        "description": "Bright yellow",
        "factoryValid": true,
        "green": 0.7686269879341125,
        "id": 2,
        "legopaletteid": 24,
        "red": 0.9960780143737793,
        "validCharacters": 1,
        "validTypes": 7
      },
      {
        "alpha": 1.0,
        "blue": 0.1568630039691925,
        "description": "Dark green",
        "factoryValid": true,
        "green": 0.48235300183296204,
        "id": 3,
        "legopaletteid": 28,
        "red": 0.0,
        "validCharacters": 1,
        "validTypes": 14
      },
      {
        "alpha": 1.0,
        "blue": 0.09411759674549103,
        "description": "Bright orange",
        "factoryValid": true,
        "green": 0.3882350027561188,
        "id": 5,
        "legopaletteid": 106,
        "red": 0.9058799743652344,
        "validCharacters": 1,
        "validTypes": 14
      },
      {
        "alpha": 1.0,
        "blue": 0.19599999487400055,
        "description": "Black",
        "factoryValid": true,
        "green": 0.19599999487400055,
        "id": 6,
        "legopaletteid": 26,
        "red": 0.19599999487400055,
        "validCharacters": 1,
        "validTypes": 14
      },
      {
        "alpha": 1.0,
        "blue": 0.33725500106811523,
        "description": "Dark stone grey",
        "factoryValid": true,
        "green": 0.3176470100879669,
        "id": 7,
        "legopaletteid": 199,
        "red": 0.2980389893054962,
        "validCharacters": 1,
        "validTypes": 14
      },
      {
        "alpha": 1.0,
        "blue": 0.550000011920929,
        "description": "Light yellowish green",
        "factoryValid": true,
        "green": 0.8899999856948853,
        "id": 71,
        "legopaletteid": 120,
        "red": 0.8399999737739563,
        "validCharacters": 0,
        "validTypes": 1
      },
      {
        "alpha": 1.0,
        "blue": 0.5699999928474426,
        "description": "Medium stone grey",
        "factoryValid": true,
        "green": 0.5699999928474426,
        "id": 8,
        "legopaletteid": 194,
        "red": 0.6100000143051147,
        "validCharacters": 1,
        "validTypes": 14
      },
      {
        "alpha": 1.0,
        "blue": 0.047058798372745514,
        "description": "Reddish brown",
        "factoryValid": false,
        "green": 0.10980399698019028,
        "id": 9,
        "legopaletteid": 192,
        "red": 0.35686299204826355,
        "validCharacters": 1,
        "validTypes": 14
      },
      {
        "alpha": 1.0,
        "blue": 0.9568629860877991,
        "description": "White",
        "factoryValid": true,
        "green": 0.9568629860877991,
        "id": 10,
        "legopaletteid": 1,
        "red": 0.9568629860877991,
        "validCharacters": 1,
        "validTypes": 14
      },
      {
        "alpha": 1.0,
        "blue": 0.7764710187911987,
        "description": "Medium blue",
        "factoryValid": true,
        "green": 0.549019992351532,
        "id": 11,
        "legopaletteid": 102,
        "red": 0.2784309983253479,
        "validCharacters": 1,
        "validTypes": 14
      },
      {
        "alpha": 1.0,
        "blue": 0.4196079969406128,
        "description": "Bright reddish violet",
        "factoryValid": true,
        "green": 0.0,
        "id": 75,
        "legopaletteid": 124,
        "red": 0.6117650270462036,
        "validCharacters": 0,
        "validTypes": 1
      },
      {
        "alpha": 1.0,
        "blue": 0.03999999910593033,
        "description": "Bright yellowish green",
        "factoryValid": true,
        "green": 0.7200000286102295,
        "id": 12,
        "legopaletteid": 119,
        "red": 0.5799999833106995,
        "validCharacters": 0,
        "validTypes": 1
      },
      {
        "alpha": 1.0,
        "blue": 0.10588199645280838,
        "description": "Dark red",
        "factoryValid": true,
        "green": 0.03137259930372238,
        "id": 13,
        "legopaletteid": 154,
        "red": 0.5019609928131104,
        "validCharacters": 1,
        "validTypes": 14
      },
      {
        "alpha": 0.5882350206375122,
        "blue": 0.7799999713897705,
        "description": "Transparent Bright bluish violet",
        "factoryValid": true,
        "green": 0.5799999833106995,
        "id": 77,
        "legopaletteid": 126,
        "red": 0.6100000143051147,
        "validCharacters": 0,
        "validTypes": 1
      },
      {
        "alpha": 1.0,
        "blue": 0.2549020051956177,
        "description": "Earth blue",
        "factoryValid": true,
        "green": 0.1450980007648468,
        "id": 14,
        "legopaletteid": 140,
        "red": 0.0,
        "validCharacters": 1,
        "validTypes": 14
      },
      {
        "alpha": 1.0,
        "blue": 0.4666669964790344,
        "description": "Medium lilac",
        "factoryValid": true,
        "green": 0.0823528990149498,
        "id": 142,
        "legopaletteid": 268,
        "red": 0.17254899442195892,
        "validCharacters": 0,
        "validTypes": 1
      },
      {
        "alpha": 1.0,
        "blue": 0.5372499823570251,
        "description": "Flesh ?",
        "factoryValid": true,
        "green": 0.7568600177764893,
        "id": 143,
        "legopaletteid": 283,
        "red": 0.9607800245285034,
        "validCharacters": 0,
        "validTypes": 1
      },
      {
        "alpha": 1.0,
        "blue": 0.08627449721097946,
        "description": "Earth green",
        "factoryValid": true,
        "green": 0.20392200350761414,
        "id": 15,
        "legopaletteid": 141,
        "red": 0.0,
        "validCharacters": 1,
        "validTypes": 14
      },
      {
        "alpha": 1.0,
        "blue": 0.47999998927116394,
        "description": "Brick Yellow",
        "factoryValid": true,
        "green": 0.7300000190734863,
        "id": 16,
        "legopaletteid": 5,
        "red": 0.8500000238418579,
        "validCharacters": 1,
        "validTypes": 14
      },
      {
        "alpha": 1.0,
        "blue": 0.7599999904632568,
        "description": "Light purple",
        "factoryValid": true,
        "green": 0.6200000047683716,
        "id": 17,
        "legopaletteid": 222,
        "red": 0.9300000071525574,
        "validCharacters": 0,
        "validTypes": 1
      },
      {
        "alpha": 1.0,
        "blue": 0.5799999833106995,
        "description": "Silver plastic",
        "factoryValid": true,
        "green": 0.5799999833106995,
        "id": 81,
        "legopaletteid": 131,
        "red": 0.550000011920929,
        "validCharacters": 0,
        "validTypes": 1
      },
      {
        "alpha": 1.0,
        "blue": 0.8352940082550049,
        "description": "Phosphorescent White replace 50",
        "factoryValid": true,
        "green": 0.9882349967956543,
        "id": 146,
        "legopaletteid": 294,
        "red": 0.9960780143737793,
        "validCharacters": 0,
        "validTypes": 1
      },
      {
        "alpha": 1.0,
        "blue": 0.4099999964237213,
        "description": "Cool yellow",
        "factoryValid": true,
        "green": 0.8899999856948853,
        "id": 18,
        "legopaletteid": 226,
        "red": 1.0,
        "validCharacters": 0,
        "validTypes": 1
      },
      {
        "alpha": 1.0,
        "blue": 0.18039199709892273,
        "description": "Warm gold",
        "factoryValid": true,
        "green": 0.49803900718688965,
        "id": 147,
        "legopaletteid": 297,
        "red": 0.6666669845581055,
        "validCharacters": 0,
        "validTypes": 1
      },
      {
        "alpha": 1.0,
        "blue": 0.250900000333786,
        "description": "Nougat",
        "factoryValid": true,
        "green": 0.44699999690055847,
        "id": 19,
        "legopaletteid": 18,
        "red": 0.8392000198364258,
        "validCharacters": 0,
        "validTypes": 1
      },
      {
        "alpha": 1.0,
        "blue": 0.549019992351532,
        "description": "Sand blue",
        "factoryValid": true,
        "green": 0.4549019932746887,
        "id": 84,
        "legopaletteid": 135,
        "red": 0.36862701177597046,
        "validCharacters": 1,
        "validTypes": 14
      },
      {
        "alpha": 1.0,
        "blue": 0.6588240265846252,
        "description": "Used for LU Metallic shader",
        "factoryValid": false,
        "green": 0.6392160058021545,
        "id": 150,
        "legopaletteid": 100001,
        "red": 0.6117650270462036,
        "validCharacters": 0,
        "validTypes": 1
      },
      {
        "alpha": 1.0,
        "blue": 0.0,
        "description": "dark brown flesh ?",
        "factoryValid": true,
        "green": 0.1294119954109192,
        "id": 151,
        "legopaletteid": 308,
        "red": 0.20392200350761414,
        "validCharacters": 0,
        "validTypes": 1
      },
      {
        "alpha": 1.0,
        "blue": 0.3199999928474426,
        "description": "Sand yellow",
        "factoryValid": true,
        "green": 0.46000000834465027,
        "id": 87,
        "legopaletteid": 138,
        "red": 0.550000011920929,
        "validCharacters": 0,
        "validTypes": 1
      },
      {
        "alpha": 1.0,
        "blue": 0.18823499977588654,
        "description": "Copper",
        "factoryValid": true,
        "green": 0.2862749993801117,
        "id": 88,
        "legopaletteid": 139,
        "red": 0.4549019932746887,
        "validCharacters": 0,
        "validTypes": 1
      },
      {
        "alpha": 0.5882350206375122,
        "blue": 0.9686269760131836,
        "description": "Transparent Fluorescent Blue",
        "factoryValid": true,
        "green": 0.8862749934196472,
        "id": 89,
        "legopaletteid": 143,
        "red": 0.8117650151252747,
        "validCharacters": 0,
        "validTypes": 1
      },
      {
        "alpha": 1.0,
        "blue": 0.23000000417232513,
        "description": "Dark grey metallic",
        "factoryValid": true,
        "green": 0.25,
        "id": 93,
        "legopaletteid": 148,
        "red": 0.2800000011920929,
        "validCharacters": 0,
        "validTypes": 1
      },
      {
        "alpha": 1.0,
        "blue": 0.3960779905319214,
        "description": "Sand green",
        "factoryValid": true,
        "green": 0.5098040103912354,
        "id": 96,
        "legopaletteid": 151,
        "red": 0.37254899740219116,
        "validCharacters": 1,
        "validTypes": 14
      },
      {
        "alpha": 1.0,
        "blue": 0.5372549891471863,
        "description": "Nature (transparent)",
        "factoryValid": false,
        "green": 0.8392159938812256,
        "id": 36,
        "legopaletteid": 20,
        "red": 0.9686269760131836,
        "validCharacters": 0,
        "validTypes": 1
      },
      {
        "alpha": 0.5882350206375122,
        "blue": 0.05490199849009514,
        "description": "Transparent bright orange",
        "factoryValid": true,
        "green": 0.4627450108528137,
        "id": 105,
        "legopaletteid": 182,
        "red": 0.9254900217056274,
        "validCharacters": 0,
        "validTypes": 1
      },
      {
        "alpha": 1.0,
        "blue": 0.1412000060081482,
        "description": "Bright green",
        "factoryValid": true,
        "green": 0.5881999731063843,
        "id": 42,
        "legopaletteid": 37,
        "red": 0.0,
        "validCharacters": 0,
        "validTypes": 1
      },
      {
        "alpha": 1.0,
        "blue": 0.08240000158548355,
        "description": "Dark orange",
        "factoryValid": true,
        "green": 0.23919999599456787,
        "id": 43,
        "legopaletteid": 38,
        "red": 0.6588000059127808,
        "validCharacters": 0,
        "validTypes": 1
      },
      {
        "alpha": 0.5882350206375122,
        "blue": 0.9333000183105469,
        "description": "Transparent",
        "factoryValid": true,
        "green": 0.9333000183105469,
        "id": 45,
        "legopaletteid": 40,
        "red": 0.9333000183105469,
        "validCharacters": 0,
        "validTypes": 1
      },
      {
        "alpha": 0.5882350206375122,
        "blue": 0.1607999950647354,
        "description": "Transparent Red",
        "factoryValid": true,
        "green": 0.1647000014781952,
        "id": 46,
        "legopaletteid": 41,
        "red": 0.8784000277519226,
        "validCharacters": 0,
        "validTypes": 1
      },
      {
        "alpha": 0.5882350206375122,
        "blue": 0.9373000264167786,
        "description": "Transparent Light blue",
        "factoryValid": true,
        "green": 0.8784000277519226,
        "id": 47,
        "legopaletteid": 42,
        "red": 0.713699996471405,
        "validCharacters": 0,
        "validTypes": 1
      },
      {
        "alpha": 0.5882350206375122,
        "blue": 0.9097999930381775,
        "description": "Transparent Blue",
        "factoryValid": true,
        "green": 0.694100022315979,
        "id": 48,
        "legopaletteid": 43,
        "red": 0.31369999051094055,
        "validCharacters": 0,
        "validTypes": 1
      },
      {
        "alpha": 1.0,
        "blue": 0.0,
        "description": "Flame yellowish orange",
        "factoryValid": true,
        "green": 0.6000000238418579,
        "id": 113,
        "legopaletteid": 191,
        "red": 0.949999988079071,
        "validCharacters": 0,
        "validTypes": 1
      },
      {
        "alpha": 0.5882350206375122,
        "blue": 0.41179999709129333,
        "description": "Transparent Yellow",
        "factoryValid": true,
        "green": 0.9373000264167786,
        "id": 49,
        "legopaletteid": 44,
        "red": 0.9764999747276306,
        "validCharacters": 0,
        "validTypes": 1
      },
      {
        "alpha": 0.5882350206375122,
        "blue": 0.27000001072883606,
        "description": "Transparent Fluorescent Reddish orange",
        "factoryValid": true,
        "green": 0.4000000059604645,
        "id": 51,
        "legopaletteid": 47,
        "red": 0.8999999761581421,
        "validCharacters": 0,
        "validTypes": 1
      },
      {
        "alpha": 0.5882350206375122,
        "blue": 0.4300000071525574,
        "description": "Transparent Green",
        "factoryValid": true,
        "green": 0.699999988079071,
        "id": 52,
        "legopaletteid": 48,
        "red": 0.38100001215934753,
        "validCharacters": 0,
        "validTypes": 1
      },
      {
        "alpha": 0.5882350206375122,
        "blue": 0.3499999940395355,
        "description": "Transparent Fluorescent Green",
        "factoryValid": true,
        "green": 0.9200000166893005,
        "id": 53,
        "legopaletteid": 49,
        "red": 0.9700000286102295,
        "validCharacters": 0,
        "validTypes": 1
      },
      {
        "alpha": 1.0,
        "blue": 0.8500000238418579,
        "description": "Light stone grey",
        "factoryValid": true,
        "green": 0.8899999856948853,
        "id": 119,
        "legopaletteid": 208,
        "red": 0.8899999856948853,
        "validCharacters": 0,
        "validTypes": 1
      },
      {
        "alpha": 1.0,
        "blue": 0.9200000166893005,
        "description": "Light Royal blue",
        "factoryValid": true,
        "green": 0.75,
        "id": 123,
        "legopaletteid": 212,
        "red": 0.5299999713897705,
        "validCharacters": 0,
        "validTypes": 1
      },
      {
        "alpha": 0.5882350206375122,
        "blue": 0.6399999856948853,
        "description": "Transparent Brown",
        "factoryValid": true,
        "green": 0.6700000166893005,
        "id": 63,
        "legopaletteid": 111,
        "red": 0.7400000095367432,
        "validCharacters": 0,
        "validTypes": 1
      }
    ]
  },
  "_links": {
    "self": {
      "href": "/lu-json/tables/BrickColors/index.json"
    }
  }
}
